pynamodb_utils/__init__.py
pynamodb_utils/attributes.py
pynamodb_utils/conditions.py
pynamodb_utils/exceptions.py
pynamodb_utils/models.py
pynamodb_utils/parsers.py
pynamodb_utils/serializers.py
pynamodb_utils/utils.py
pynamodb_utils-1.5.1.dist-info/LICENSE
pynamodb_utils-1.5.1.dist-info/METADATA
pynamodb_utils-1.5.1.dist-info/WHEEL
pynamodb_utils-1.5.1.dist-info/top_level.txt
pynamodb_utils-1.5.1.dist-info/RECORD
