Metadata-Version: 2.1
Name: pynamodb-utils
Version: 1.5.1
Summary: Utilities package for pynamodb.
Home-page: https://github.com/micmurawski/pynamodb-utils/
Author: Michal Murawski
Author-email: mmurawski777@gmail.com
License: MIT
Platform: UNKNOWN
Classifier: License :: OSI Approved :: MIT License
Classifier: Programming Language :: Python :: 3
Classifier: Programming Language :: Python :: 3.6
Classifier: Programming Language :: Python :: 3.7
Classifier: Programming Language :: Python :: 3.8
Requires-Python: >=3.6
License-File: LICENSE
Requires-Dist: pynamodb (<7.0.0,>=6.0.0)
